paypay/__init__.py
paypay/main.py
paypay-0.1.0.dist-info/WHEEL
paypay-0.1.0.dist-info/METADATA
paypay-0.1.0.dist-info/RECORD
